whill/__init__.py
whill/whill.py
whill/whill_data.py
whill/whill_packet.py
whill-1.5.0.dist-info/LICENSE
whill-1.5.0.dist-info/METADATA
whill-1.5.0.dist-info/WHEEL
whill-1.5.0.dist-info/top_level.txt
whill-1.5.0.dist-info/RECORD
