Metadata-Version: 2.1
Name: whill
Version: 1.5.0
Summary: WHILL Model CR series SDK for Python
Home-page: https://whill.inc/jp/model-cr2
Author: Seiya Shimizu
Author-email: seiya.shimizu@whill.inc
Maintainer: George Mandokoro
Maintainer-email: george.mandokoro@whill.inc
Requires-Python: >=3.6,<4.0
License-File: LICENSE
Requires-Dist: pyserial <4.0,>=3.5
